README.md
setup.py
gevent_tools.egg-info/PKG-INFO
gevent_tools.egg-info/SOURCES.txt
gevent_tools.egg-info/dependency_links.txt
gevent_tools.egg-info/requires.txt
gevent_tools.egg-info/top_level.txt
gtools/__init__.py
gtools/base.py
gtools/greenlet.py
gtools/monkey.py
gtools/multistd.py
gtools/pdb.py
gtools/tree.py
gtools/version.py
gtools/xmlrpc/__init__.py
gtools/xmlrpc/client.py